{
  "id": "wind_06",
  "name": "Tempestade Dupla",
  "description": "Dois ventos opostos criam um padr\u00e3o ca\u00f3tico.",
  "difficulty": 6,
  "timeGoalSeconds": 135,
  "playerSpawn": {
    "x": 100,
    "y": 500
  },
  "goal": {
    "x": 725,
    "y": 75,
    "radius": 30
  },
  "platforms": [
    {
      "x": 400,
      "y": 550,
      "width": 800,
      "height": 50
    },
    {
      "x": 250,
      "y": 350,
      "width": 100,
      "height": 30
    },
    {
      "x": 400,
      "y": 250,
      "width": 100,
      "height": 30
    },
    {
      "x": 550,
      "y": 150,
      "width": 100,
      "height": 30
    },
    {
      "x": 700,
      "y": 50,
      "width": 100,
      "height": 30
    }
  ],
  "hazards": [
    {
      "type": "spikes",
      "x": 200,
      "y": 520,
      "width": 80,
      "height": 30
    },
    {
      "type": "spikes",
      "x": 350,
      "y": 420,
      "width": 80,
      "height": 30
    },
    {
      "type": "spikes",
      "x": 500,
      "y": 320,
      "width": 80,
      "height": 30
    }
  ],
  "collectibles": [
    {
      "x": 100,
      "y": 400,
      "id": "coin_1"
    },
    {
      "x": 400,
      "y": 300,
      "id": "coin_2"
    },
    {
      "x": 700,
      "y": 200,
      "id": "coin_3"
    }
  ],
  "windZones": [
    {
      "x": 150,
      "y": 200,
      "width": 250,
      "height": 250,
      "forceX": 150,
      "forceY": -50,
      "type": "pulsed",
      "pulseDuration": 800
    },
    {
      "x": 350,
      "y": 250,
      "width": 250,
      "height": 250,
      "forceX": 200,
      "forceY": -70,
      "type": "constant"
    }
  ],
  "movingPlatforms": [],
  "checkpoints": [],
  "hints": [
    "Dica 6 - Fase 6",
    "Observe o padr\u00e3o do vento n\u00edvel 6",
    "Voc\u00ea consegue completar em 135 segundos?"
  ]
}